{
  "placeholderImages": [
    {
      "id": "hero-background",
      "description": "A modern and clean medical clinic interior.",
      "imageUrl": "https://www.infoblancosobrenegro.com/uploads/noticias/5/2024/08/20240819195557_estetica.jpg",
      "imageHint": "medical clinic"
    },
    {
      "id": "laseev-pro-machine",
      "description": "The LASEEV Pro endolaser machine on a clean background.",
      "imageUrl": "https://i.imgur.com/mFEzwMl.jpeg",
      "imageHint": "medical equipment"
    },
    {
      "id": "laseev-endolifting",
      "description": "Close-up of a laser lipolysis procedure on the chin area.",
      "imageUrl": "https://i.imgur.com/gYfX3zW.jpeg",
      "imageHint": "laser lipolysis"
    },
    {
      "id": "laseev-vascular",
      "description": "Treatment of spider veins on a leg.",
      "imageUrl": "https://i.imgur.com/s6n5F3p.jpeg",
      "imageHint": "spider veins"
    },
    {
      "id": "laseev-onicomicosis",
      "description": "Laser treatment for toenail fungus.",
      "imageUrl": "https://i.imgur.com/O6P2j7W.jpeg",
      "imageHint": "toenail fungus"
    },
    {
      "id": "laseev-vaginal",
      "description": "Abstract image representing vaginal rejuvenation.",
      "imageUrl": "https://i.imgur.com/kS9w1h8.jpeg",
      "imageHint": "abstract female health"
    },
    {
      "id": "laseev-evlt",
      "description": "Doctor performing an endovenous laser treatment on a patient's leg.",
      "imageUrl": "https://i.imgur.com/8Q0vY6j.jpeg",
      "imageHint": "varicose veins treatment"
    },
    {
      "id": "laseev-pldd",
      "description": "Medical illustration of a herniated disc.",
      "imageUrl": "https://i.imgur.com/uTj8fO7.jpeg",
      "imageHint": "herniated disc"
    },
    {
      "id": "laseev-ent",
      "description": "An ENT specialist using medical equipment.",
      "imageUrl": "https://i.imgur.com/d9j8v2L.jpeg",
      "imageHint": "ent specialist"
    },
    {
      "id": "laseev-dental",
      "description": "Dentist performing a laser procedure on a patient.",
      "imageUrl": "https://i.imgur.com/T5I2o4W.jpeg",
      "imageHint": "dental laser"
    },
    {
      "id": "laseev-physio",
      "description": "Physiotherapist applying laser therapy to a patient's shoulder.",
      "imageUrl": "https://i.imgur.com/x0q4w9j.jpeg",
      "imageHint": "laser physiotherapy"
    },
    {
      "id": "laseev-proctology",
      "description": "Abstract medical image related to proctology.",
      "imageUrl": "https://i.imgur.com/5J3c2z5.jpeg",
      "imageHint": "medical surgery"
    },
    {
      "id": "treatment-endolifting",
      "description": "A patient receiving a non-invasive facial treatment.",
      "imageUrl": "https://i.imgur.com/clViTJF.jpeg",
      "imageHint": "facial treatment"
    },
    {
      "id": "treatment-lipomela",
      "description": "Body contouring procedure.",
      "imageUrl": "https://i.imgur.com/qc5SWHJ.jpeg",
      "imageHint": "body contouring"
    },
    {
      "id": "treatment-armonizacion",
      "description": "Close up of a facial harmonization procedure with injectables.",
      "imageUrl": "https://i.imgur.com/RdgVp83.jpeg",
      "imageHint": "facial injection"
    },
    {
      "id": "treatment-faloplastia",
      "description": "Abstract medical image related to men's health.",
      "imageUrl": "https://i.imgur.com/uCCju4r.jpeg",
      "imageHint": "medical abstract"
    },
    {
      "id": "treatment-rinomodelacion",
      "description": "Profile view of a face showing nose before and after.",
      "imageUrl": "https://i.imgur.com/KIuHuUj.jpeg",
      "imageHint": "face profile"
    },
    {
      "id": "course-endolaser",
      "description": "Doctors in a training session with medical equipment.",
      "imageUrl": "https://i.imgur.com/JhYikLR.jpeg",
      "imageHint": "medical training"
    },
    {
      "id": "course-botox",
      "description": "A doctor teaching about facial injection points.",
      "imageUrl": "https://i.imgur.com/JrmnTYM.jpeg",
      "imageHint": "medical lecture"
    },
    {
      "id": "course-armonizacion",
      "description": "Hands-on training for facial aesthetics.",
      "imageUrl": "https://i.imgur.com/uwkhWmZ.jpeg",
      "imageHint": "aesthetic training"
    },
    {
      "id": "course-vascular",
      "description": "A close-up of a vascular laser treatment.",
      "imageUrl": "https://i.imgur.com/a6OVnf2.jpeg",
      "imageHint": "laser treatment"
    },
    {
      "id": "course-faloplastia",
      "description": "A professional medical seminar setting.",
      "imageUrl": "https://i.imgur.com/DKBbus3.jpeg",
      "imageHint": "medical seminar"
    },
    {
      "id": "course-labioplastia",
      "description": "A professional medical seminar about female procedures.",
      "imageUrl": "https://i.imgur.com/DhuKg1m.jpeg",
      "imageHint": "medical conference"
    },
    {
      "id": "course-rinomodelacion",
      "description": "A doctor explaining rhinomodelation to a patient.",
      "imageUrl": "https://i.imgur.com/6ACEk8f.jpeg",
      "imageHint": "rhinoplasty consultation"
    },
    {
      "id": "course-mela",
      "description": "Practical training on body contouring techniques.",
      "imageUrl": "https://i.imgur.com/9hvYsBl.jpeg",
      "imageHint": "body contouring"
    },
    {
      "id": "mister-dog-grooming",
      "description": "A happy dog being groomed.",
      "imageUrl": "https://i.imgur.com/DTWt3im.jpeg",
      "imageHint": "dog grooming"
    },
    {
      "id": "mister-dog-course",
      "description": "A person teaching how to groom a dog.",
      "imageUrl": "https://i.imgur.com/ukhOKYT.jpeg",
      "imageHint": "dog training"
    },
    {
      "id": "feature-wavelength",
      "description": "Abstract graphic showing laser wavelengths.",
      "imageUrl": "https://i.imgur.com/y1vRZNz.jpeg",
      "imageHint": "laser wavelength"
    },
    {
      "id": "feature-warranty",
      "description": "A warranty seal or certificate.",
      "imageUrl": "https://i.imgur.com/f2n5pL0.jpeg",
      "imageHint": "warranty seal"
    },
    {
      "id": "feature-training",
      "description": "A group of professionals in a training session.",
      "imageUrl": "https://i.imgur.com/x0q4w9j.jpeg",
      "imageHint": "professional training"
    }
  ]
}